<?xml version="1.0" encoding="UTF-8"?>
<!DOCTYPE suite SYSTEM "http://testng.org/testng-1.0.dtd">

<suite name="All Test Suite">
    <test verbose="2" preserve-order="true" name="C:/Users/Friday/IdeaProjects/Api_TestNg/src/test/java/api/test/UserTest.java">
        <classes>
            <class name="api.test.UserTest">
                <methods>
                    <include name="createAnUser"/>
                    <include name="testGetUserByName"/>
                    <include name="updateByName"/>
                    <include name="deleteUserdata"/>
                </methods>
            </class>
        </classes>
    </test>
</suite>